a_law_lib/__init__.py
a_law_lib/main.py
a_law_lib-0.2.0.dist-info/METADATA
a_law_lib-0.2.0.dist-info/WHEEL
a_law_lib-0.2.0.dist-info/top_level.txt
a_law_lib-0.2.0.dist-info/RECORD
